db_zpark_pyf/__init__.py
db_zpark_pyf/workflow_subtask.py
db_zpark_pyf/workflow_subtasks_runner.py
db_zpark_pyf/workflow_task.py
db_zpark_pyf-0.1.0.dist-info/LICENSE
db_zpark_pyf-0.1.0.dist-info/METADATA
db_zpark_pyf-0.1.0.dist-info/WHEEL
db_zpark_pyf-0.1.0.dist-info/RECORD
