Metadata-Version: 2.3
Name: db_zpark_pyf
Version: 0.1.0
Summary: A code-first approach to managing PySpark jobs, built on the pyfecto framework and geared for Databricks environments
License: MIT
Author: fernanluyano
Requires-Python: >=3.11,<4.0
Classifier: License :: OSI Approved :: MIT License
Classifier: Programming Language :: Python :: 3
Classifier: Programming Language :: Python :: 3.11
Classifier: Programming Language :: Python :: 3.12
Classifier: Programming Language :: Python :: 3.13
Requires-Dist: gitpython (>=3.1.0,<4.0.0)
Requires-Dist: pyfecto (>=0.2.0,<0.3.0)
